{
  "total": 23056,
  "success": 9311,
  "failed": 2217,
  "by_country": {
    "IR": 6279,
    "US": 876,
    "CDN": 175,
    "NL": 420,
    "DE": 1380,
    "SG": 57,
    "TR": 124
  },
  "by_protocol": {
    "vless": 7690,
    "hysteria": 2,
    "trojan": 268,
    "vmess": 494,
    "ss": 857
  },
  "by_transport": {
    "ws": 3102,
    "tcp": 4592,
    "grpc": 1086,
    "http": 526,
    "udp": 2,
    "kcp": 1,
    "httpupgrade": 1,
    "xhttp": 1
  },
  "with_tls": 8152,
  "without_tls": 1159,
  "cdn_count": 175
}